pymmh3/__init__.py
pymmh3/pymmh3.py
pymmh3-0.0.4.dist-info/LICENSE.txt
pymmh3-0.0.4.dist-info/METADATA
pymmh3-0.0.4.dist-info/WHEEL
pymmh3-0.0.4.dist-info/top_level.txt
pymmh3-0.0.4.dist-info/RECORD
